ERgene/ERgene.py
ERgene/__init__.py
ERgene-1.2.8.dist-info/METADATA
ERgene-1.2.8.dist-info/RECORD
ERgene-1.2.8.dist-info/WHEEL
ERgene-1.2.8.dist-info/top_level.txt
