Metadata-Version: 2.1
Name: ERgene
Version: 1.2.8
Summary: A python module that could analysis the ERGs
Home-page: https://github.com/Starlitnightly/ERgene
Author: ZehuaZeng
Author-email: Starlitnightly@163.com
License: MIT License
Platform: UNKNOWN
Requires-Dist: upsetplot
